b9y_cli/__init__.py
b9y_cli/__main__.py
b9y_cli-0.1.34.dist-info/LICENSE
b9y_cli-0.1.34.dist-info/METADATA
b9y_cli-0.1.34.dist-info/WHEEL
b9y_cli-0.1.34.dist-info/entry_points.txt
b9y_cli-0.1.34.dist-info/top_level.txt
b9y_cli-0.1.34.dist-info/RECORD
