Metadata-Version: 2.1
Name: b9y-cli
Version: 0.1.34
Summary: Commandline Interface for Bambleweeny
Home-page: https://github.com/u1i/b9y-cli
Author: Uli Hitzel
Author-email: uli.hitzel@gmail.com
License: UNKNOWN
Platform: UNKNOWN
Classifier: Programming Language :: Python :: 2
Classifier: License :: OSI Approved :: MIT License
Classifier: Operating System :: OS Independent
Requires-Dist: b9y
